airflow/providers/sendgrid/__init__.py
airflow/providers/sendgrid/get_provider_info.py
airflow/providers/sendgrid/version_compat.py
airflow/providers/sendgrid/utils/__init__.py
airflow/providers/sendgrid/utils/emailer.py
apache_airflow_providers_sendgrid-4.2.1.dist-info/entry_points.txt
apache_airflow_providers_sendgrid-4.2.1.dist-info/licenses/LICENSE
apache_airflow_providers_sendgrid-4.2.1.dist-info/licenses/NOTICE
apache_airflow_providers_sendgrid-4.2.1.dist-info/WHEEL
apache_airflow_providers_sendgrid-4.2.1.dist-info/METADATA
apache_airflow_providers_sendgrid-4.2.1.dist-info/RECORD
